{"hash":"0d54d7d3893fe733e4f5ab95398fd89ff3abea73","data":{"posts":{"totalCount":2,"pageInfo":{"totalPages":1,"currentPage":1},"edges":[{"node":{"id":"1f2beebb7fea92ab5d8442cd4ef85a30","title":"Build an API using NodeJS and ExpressJS","date":"February 3, 2020","summary":"REST or RESTful stands for REpresentational State Transfer. It is an architectural style as well as an approach for communications purposes that is often used in various web services development. In simpler terms, it is an application program interface (API) that makes use of the HTTP requests to GET, PUT, POST and DELETE the data over WWW.","timeToRead":5,"path":"/api-using-node-expressjs"}},{"node":{"id":"4a4f8664771a468fafa1fc86b781dfc2","title":"Introduction to Gridsome","date":"June 19, 2019","summary":"Gridsome is a Vue.js-powered, modern site generator for building the fastest possible websites for any Headless CMS, APIs or Markdown-files. Gridsome makes it easy and fun for developers to create fast, beautiful websites without needing to become a performance expert.","timeToRead":1,"path":"/introduction-to-gridsome"}}]}},"context":{}}